topsis/__init__.py
Topsis_Harpreet_101803193-1.1.3.dist-info/LICENSE.txt
Topsis_Harpreet_101803193-1.1.3.dist-info/METADATA
Topsis_Harpreet_101803193-1.1.3.dist-info/WHEEL
Topsis_Harpreet_101803193-1.1.3.dist-info/top_level.txt
Topsis_Harpreet_101803193-1.1.3.dist-info/RECORD
