Metadata-Version: 2.1
Name: Topsis-Harpreet-101803193
Version: 1.1.3
Summary: Implements Topsis
Home-page: UNKNOWN
Author: Harpreet singh
Author-email: harpreetng22@gmail.com
License: MIT
Platform: UNKNOWN
Classifier: License :: OSI Approved :: MIT License
Classifier: Programming Language :: Python :: 3.6
Classifier: Programming Language :: Python :: 3.7
Classifier: Programming Language :: Python :: 3.8
Requires-Dist: pandas
Requires-Dist: numpy
